DNAsplot/DNAsplot.py
DNAsplot/__init__.py
DNAsplot/__main__.py
DNAsplot/_version.py
DNAsplot-1.0.7.dist-info/LICENSE
DNAsplot-1.0.7.dist-info/METADATA
DNAsplot-1.0.7.dist-info/WHEEL
DNAsplot-1.0.7.dist-info/entry_points.txt
DNAsplot-1.0.7.dist-info/top_level.txt
DNAsplot-1.0.7.dist-info/RECORD
