Metadata-Version: 2.1
Name: DNAsplot
Version: 1.0.7
Summary: plot multiple DNA sequences with point mutations
Home-page: https://pypi.org/project/DNAsplot/
Author: Benxia Hu
Author-email: hubenxia@gmail.com
License: UNKNOWN
Platform: UNKNOWN
Classifier: Programming Language :: Python :: 3
Classifier: License :: OSI Approved :: MIT License
Classifier: Operating System :: OS Independent
Requires-Python: >=3.6
Requires-Dist: pandas
Requires-Dist: argparse
Requires-Dist: matplotlib
